pygray/__init__.py
pygray/_version.py
pygray/cli.py
pygray/dateutils.py
pygray/formats.py
pygray/graylog_api.py
pygray/input.py
pygray/output.py
pygray/utils.py
pygray-0.9.5.dist-info/DESCRIPTION.rst
pygray-0.9.5.dist-info/METADATA
pygray-0.9.5.dist-info/RECORD
pygray-0.9.5.dist-info/WHEEL
pygray-0.9.5.dist-info/entry_points.txt
pygray-0.9.5.dist-info/metadata.json
pygray-0.9.5.dist-info/top_level.txt
