Metadata-Version: 2.0
Name: pygray
Version: 0.9.5
Summary: Graylog command line interface (pygray fork).
Home-page: https://github.com/joaomarcusc/pygray
Author: Joao Marcus Christ
Author-email: joaoma@gmail.com
License: Apache Software License 2.0
Keywords: pygray
Platform: UNKNOWN
Classifier: Development Status :: 3 - Alpha
Classifier: Intended Audience :: Developers
Classifier: License :: OSI Approved :: Apache Software License
Classifier: Natural Language :: English
Classifier: Programming Language :: Python :: 3
Classifier: Programming Language :: Python :: 3.5
Classifier: Programming Language :: Python :: 3.6
Classifier: Programming Language :: Python :: 3.7
Requires-Dist: arrow (<0.8,>=0.5.4)
Requires-Dist: click (<7,>=3.3)
Requires-Dist: keyring (==8.7)
Requires-Dist: parsedatetime (>=2.4,<3)
Requires-Dist: python-dateutil (<3,>=2.4.1)
Requires-Dist: requests (<3.0,>=2.4.3)
Requires-Dist: six (>=1.9.0)
Requires-Dist: termcolor (==1.1.0)
